glcr.cp36-win_amd64.pyd
glcr-1.1.1.dist-info/LICENSE
glcr-1.1.1.dist-info/METADATA
glcr-1.1.1.dist-info/WHEEL
glcr-1.1.1.dist-info/top_level.txt
glcr-1.1.1.dist-info/RECORD
